LICENSE
README.md
setup.py
hello_world/__init__.py
hello_world/hello_world.py
teste_nuget_python.egg-info/PKG-INFO
teste_nuget_python.egg-info/SOURCES.txt
teste_nuget_python.egg-info/dependency_links.txt
teste_nuget_python.egg-info/top_level.txt