Metadata-Version: 2.1
Name: teste-nuget-python
Version: 1.0.1
Summary: Um pacote de teste para aprender a criar pacotes com o Python
Home-page: UNKNOWN
Author: Ricardo Braga
Author-email: rickalbbraga@gmail.com
License: MIT License
Keywords: hello world
Platform: UNKNOWN
License-File: LICENSE
